{
  "version": "0.1.0-alpha.1",
  "releaseTag": "v0.1.0-alpha.1",
  "releaseDate": null,
  "releasePublished": false,
  "repositoryUrl": "https://github.com/mann-lab-apps/in-c",
  "releaseUrl": "https://github.com/mann-lab-apps/in-c/releases",
  "checksumsUrl": "https://github.com/mann-lab-apps/in-c/releases",
  "signing": {
    "macOS": "미서명 prerelease. Gatekeeper 경고가 표시될 수 있습니다.",
    "Windows": "미서명 prerelease. SmartScreen 경고가 표시될 수 있습니다.",
    "Linux": "미서명 AppImage. 실행 권한을 직접 부여해야 할 수 있습니다."
  },
  "downloads": [
    {
      "id": "macos",
      "platform": "macOS",
      "label": "macOS",
      "architecture": "Universal",
      "format": "DMG",
      "available": false,
      "fileName": "in-C-0.1.0-alpha.1-mac-universal.dmg",
      "size": null,
      "url": null
    },
    {
      "id": "windows",
      "platform": "Windows",
      "label": "Windows",
      "architecture": "x64",
      "format": "NSIS installer",
      "available": false,
      "fileName": "in-C-0.1.0-alpha.1-windows-x64-setup.exe",
      "size": null,
      "url": null
    },
    {
      "id": "linux",
      "platform": "Linux",
      "label": "Linux",
      "architecture": "x64",
      "format": "AppImage",
      "available": false,
      "fileName": "in-C-0.1.0-alpha.1-linux-x64.AppImage",
      "size": null,
      "url": null
    }
  ]
}
